LICENSE
MANIFEST.in
README.rst
setup.py
logdag/__init__.py
logdag/__main__.py
logdag/arguments.py
logdag/cdt_input.py
logdag/dtutil.py
logdag/lingam_input.py
logdag/log2event.py
logdag/makedag.py
logdag/mixedlingam_input.py
logdag/pc_input.py
logdag/pknowledge.py
logdag/showdag.py
logdag/showdag_filter.py
logdag/tsdb.py
logdag.egg-info/PKG-INFO
logdag.egg-info/SOURCES.txt
logdag.egg-info/dependency_links.txt
logdag.egg-info/entry_points.txt
logdag.egg-info/requires.txt
logdag.egg-info/top_level.txt
logdag/data/area_def.txt.sample
logdag/data/config.conf.default
logdag/data/config.conf.old
logdag/data/list_rt_if
logdag/data/list_rt_info